tonetint/__init__.py
tonetint/sentiment_visualizer.py
tonetint-0.0.15.dist-info/METADATA
tonetint-0.0.15.dist-info/WHEEL
tonetint-0.0.15.dist-info/licenses/LICENCE
tonetint-0.0.15.dist-info/RECORD
