Metadata-Version: 2.3
Name: tonetint
Version: 0.0.15
Summary: ToneTint is a Python package that provides an intuitive way to perform sentiment analysis on text data and visualize the results. It splits the input text into manageable chunks, analyzes each chunk using a pre-trained sentiment analysis model, and highlights the text with background colors corresponding to the sentiment. Additionally, it displays tooltips with detailed sentiment scores when hovering over each text chunk.
Project-URL: Homepage, https://github.com/janduplessis883/tonetint_package
Project-URL: Issues, https://github.com/janduplessis883/tonetint_package/issues
Author-email: Jan du Plessis <drjanduplessis@icloud.com>
License-File: LICENCE
Classifier: License :: OSI Approved :: MIT License
Classifier: Operating System :: OS Independent
Classifier: Programming Language :: Python :: 3
Requires-Python: >=3.8
Requires-Dist: ipython
Requires-Dist: nltk
Requires-Dist: sentencepiece
Requires-Dist: streamlit
Requires-Dist: torch
Requires-Dist: transformers
